Workbook

Sheet Resumo
A1: Controle financeiro pessoal (dados simulados)
A2: Escolha o mês na célula amarela. Período: out/2025 a set/2026. Tudo é calculado por fórmulas.
A4: Mês selecionado | B4: 46266
A6: Receitas do mês | B6: Despesas do mês | C6: Saldo do mês | D6: Taxa de poupança | E6: Orçamento usado
A7: =SUMIFS(Lancamentos!$F$2:$F$482,Lancamentos!$E$2:$E$482,"Receita",Lancamentos!$H$2:$H$482,$B$4) -> 5628.35 | B7: =SUMIFS(Lancamentos!$F$2:$F$482,Lancamentos!$E$2:$E$482,"Despesa",Lancamentos!$H$2:$H$482,$B$4) -> 4769.98 | C7: =A7-B7 -> 858.37 | D7: =IFERROR(C7/A7,0) -> 0.15250828 | E7: =IFERROR(B7/Orcamento!B11,0) -> 0.95975453
A9: Orçado x realizado no mês selecionado
A10: Categoria | B10: Orçado | C10: Realizado | D10: Diferença | E10: % usado | F10: Status
A11: =Orcamento!A2 -> Moradia | B11: =Orcamento!B2 -> 1900 | C11: =SUMIFS(Lancamentos!$F$2:$F$482,Lancamentos!$D$2:$D$482,A11,Lancamentos!$E$2:$E$482,"Despesa",Lancamentos!$H$2:$H$482,$B$4) -> 1829.05 | D11: =B11-C11 -> 70.95 | E11: =IFERROR(C11/B11,0) -> 0.96265789 | F11: =IF(E11>1,"Estourou",IF(E11>0.9,"Atenção","OK")) -> Atenção
A12: =Orcamento!A3 -> Alimentação | B12: =Orcamento!B3 -> 1100 | C12: =SUMIFS(Lancamentos!$F$2:$F$482,Lancamentos!$D$2:$D$482,A12,Lancamentos!$E$2:$E$482,"Despesa",Lancamentos!$H$2:$H$482,$B$4) -> 1499.42 | D12: =B12-C12 -> -399.42 | E12: =IFERROR(C12/B12,0) -> 1.3631091 | F12: =IF(E12>1,"Estourou",IF(E12>0.9,"Atenção","OK")) -> Estourou
A13: =Orcamento!A4 -> Transporte | B13: =Orcamento!B4 -> 450 | C13: =SUMIFS(Lancamentos!$F$2:$F$482,Lancamentos!$D$2:$D$482,A13,Lancamentos!$E$2:$E$482,"Despesa",Lancamentos!$H$2:$H$482,$B$4) -> 338.38 | D13: =B13-C13 -> 111.62 | E13: =IFERROR(C13/B13,0) -> 0.75195556 | F13: =IF(E13>1,"Estourou",IF(E13>0.9,"Atenção","OK")) -> OK
A14: =Orcamento!A5 -> Saúde | B14: =Orcamento!B5 -> 250 | C14: =SUMIFS(Lancamentos!$F$2:$F$482,Lancamentos!$D$2:$D$482,A14,Lancamentos!$E$2:$E$482,"Despesa",Lancamentos!$H$2:$H$482,$B$4) -> 214.64 | D14: =B14-C14 -> 35.36 | E14: =IFERROR(C14/B14,0) -> 0.85856 | F14: =IF(E14>1,"Estourou",IF(E14>0.9,"Atenção","OK")) -> OK
A15: =Orcamento!A6 -> Lazer | B15: =Orcamento!B6 -> 400 | C15: =SUMIFS(Lancamentos!$F$2:$F$482,Lancamentos!$D$2:$D$482,A15,Lancamentos!$E$2:$E$482,"Despesa",Lancamentos!$H$2:$H$482,$B$4) -> 490 | D15: =B15-C15 -> -90 | E15: =IFERROR(C15/B15,0) -> 1.225 | F15: =IF(E15>1,"Estourou",IF(E15>0.9,"Atenção","OK")) -> Estourou
A16: =Orcamento!A7 -> Educação | B16: =Orcamento!B7 -> 200 | C16: =SUMIFS(Lancamentos!$F$2:$F$482,Lancamentos!$D$2:$D$482,A16,Lancamentos!$E$2:$E$482,"Despesa",Lancamentos!$H$2:$H$482,$B$4) -> 59.9 | D16: =B16-C16 -> 140.1 | E16: =IFERROR(C16/B16,0) -> 0.2995 | F16: =IF(E16>1,"Estourou",IF(E16>0.9,"Atenção","OK")) -> OK
A17: =Orcamento!A8 -> Assinaturas | B17: =Orcamento!B8 -> 120 | C17: =SUMIFS(Lancamentos!$F$2:$F$482,Lancamentos!$D$2:$D$482,A17,Lancamentos!$E$2:$E$482,"Despesa",Lancamentos!$H$2:$H$482,$B$4) -> 61.8 | D17: =B17-C17 -> 58.2 | E17: =IFERROR(C17/B17,0) -> 0.515 | F17: =IF(E17>1,"Estourou",IF(E17>0.9,"Atenção","OK")) -> OK
A18: =Orcamento!A9 -> Compras | B18: =Orcamento!B9 -> 350 | C18: =SUMIFS(Lancamentos!$F$2:$F$482,Lancamentos!$D$2:$D$482,A18,Lancamentos!$E$2:$E$482,"Despesa",Lancamentos!$H$2:$H$482,$B$4) -> 128.05 | D18: =B18-C18 -> 221.95 | E18: =IFERROR(C18/B18,0) -> 0.36585714 | F18: =IF(E18>1,"Estourou",IF(E18>0.9,"Atenção","OK")) -> OK
A19: =Orcamento!A10 -> Outros | B19: =Orcamento!B10 -> 200 | C19: =SUMIFS(Lancamentos!$F$2:$F$482,Lancamentos!$D$2:$D$482,A19,Lancamentos!$E$2:$E$482,"Despesa",Lancamentos!$H$2:$H$482,$B$4) -> 148.74 | D19: =B19-C19 -> 51.26 | E19: =IFERROR(C19/B19,0) -> 0.7437 | F19: =IF(E19>1,"Estourou",IF(E19>0.9,"Atenção","OK")) -> OK
A20: Total | B20: =SUM(B11:B19) -> 4970 | C20: =SUM(C11:C19) -> 4769.98 | D20: =B20-C20 -> 200.02 | E20: =IFERROR(C20/B20,0) -> 0.95975453
A22: Visão anual
A23: Mês | B23: Receitas | C23: Despesas | D23: Saldo | E23: Taxa de poupança | F23: Saldo acumulado
A24: =Listas!A2 -> 45931 | B24: =SUMIFS(Lancamentos!$F$2:$F$482,Lancamentos!$E$2:$E$482,"Receita",Lancamentos!$H$2:$H$482,A24) -> 5618.75 | C24: =SUMIFS(Lancamentos!$F$2:$F$482,Lancamentos!$E$2:$E$482,"Despesa",Lancamentos!$H$2:$H$482,A24) -> 4110.09 | D24: =B24-C24 -> 1508.66 | E24: =IFERROR(D24/B24,0) -> 0.26850456 | F24: =D24 -> 1508.66
A25: =Listas!A3 -> 45962 | B25: =SUMIFS(Lancamentos!$F$2:$F$482,Lancamentos!$E$2:$E$482,"Receita",Lancamentos!$H$2:$H$482,A25) -> 6590.98 | C25: =SUMIFS(Lancamentos!$F$2:$F$482,Lancamentos!$E$2:$E$482,"Despesa",Lancamentos!$H$2:$H$482,A25) -> 4528.15 | D25: =B25-C25 -> 2062.83 | E25: =IFERROR(D25/B25,0) -> 0.31297774 | F25: =F24+D25 -> 3571.49
A26: =Listas!A4 -> 45992 | B26: =SUMIFS(Lancamentos!$F$2:$F$482,Lancamentos!$E$2:$E$482,"Receita",Lancamentos!$H$2:$H$482,A26) -> 5647.34 | C26: =SUMIFS(Lancamentos!$F$2:$F$482,Lancamentos!$E$2:$E$482,"Despesa",Lancamentos!$H$2:$H$482,A26) -> 4855.54 | D26: =B26-C26 -> 791.8 | E26: =IFERROR(D26/B26,0) -> 0.1402076 | F26: =F25+D26 -> 4363.29
A27: =Listas!A5 -> 46023 | B27: =SUMIFS(Lancamentos!$F$2:$F$482,Lancamentos!$E$2:$E$482,"Receita",Lancamentos!$H$2:$H$482,A27) -> 5645.07 | C27: =SUMIFS(Lancamentos!$F$2:$F$482,Lancamentos!$E$2:$E$482,"Despesa",Lancamentos!$H$2:$H$482,A27) -> 3862.58 | D27: =B27-C27 -> 1782.49 | E27: =IFERROR(D27/B27,0) -> 0.31576048 | F27: =F26+D27 -> 6145.78
A28: =Listas!A6 -> 46054 | B28: =SUMIFS(Lancamentos!$F$2:$F$482,Lancamentos!$E$2:$E$482,"Receita",Lancamentos!$H$2:$H$482,A28) -> 5636.35 | C28: =SUMIFS(Lancamentos!$F$2:$F$482,Lancamentos!$E$2:$E$482,"Despesa",Lancamentos!$H$2:$H$482,A28) -> 4396.25 | D28: =B28-C28 -> 1240.1 | E28: =IFERROR(D28/B28,0) -> 0.22001827 | F28: =F27+D28 -> 7385.88
A29: =Listas!A7 -> 46082 | B29: =SUMIFS(Lancamentos!$F$2:$F$482,Lancamentos!$E$2:$E$482,"Receita",Lancamentos!$H$2:$H$482,A29) -> 6216.14 | C29: =SUMIFS(Lancamentos!$F$2:$F$482,Lancamentos!$E$2:$E$482,"Despesa",Lancamentos!$H$2:$H$482,A29) -> 4669.01 | D29: =B29-C29 -> 1547.13 | E29: =IFERROR(D29/B29,0) -> 0.24888918 | F29: =F28+D29 -> 8933.01
A30: =Listas!A8 -> 46113 | B30: =SUMIFS(Lancamentos!$F$2:$F$482,Lancamentos!$E$2:$E$482,"Receita",Lancamentos!$H$2:$H$482,A30) -> 6228.12 | C30: =SUMIFS(Lancamentos!$F$2:$F$482,Lancamentos!$E$2:$E$482,"Despesa",Lancamentos!$H$2:$H$482,A30) -> 4743.84 | D30: =B30-C30 -> 1484.28 | E30: =IFERROR(D30/B30,0) -> 0.23831911 | F30: =F29+D30 -> 10417.29
A31: =Listas!A9 -> 46143 | B31: =SUMIFS(Lancamentos!$F$2:$F$482,Lancamentos!$E$2:$E$482,"Receita",Lancamentos!$H$2:$H$482,A31) -> 5641.94 | C31: =SUMIFS(Lancamentos!$F$2:$F$482,Lancamentos!$E$2:$E$482,"Despesa",Lancamentos!$H$2:$H$482,A31) -> 4814.07 | D31: =B31-C31 -> 827.87 | E31: =IFERROR(D31/B31,0) -> 0.14673499 | F31: =F30+D31 -> 11245.16
A32: =Listas!A10 -> 46174 | B32: =SUMIFS(Lancamentos!$F$2:$F$482,Lancamentos!$E$2:$E$482,"Receita",Lancamentos!$H$2:$H$482,A32) -> 5631.06 | C32: =SUMIFS(Lancamentos!$F$2:$F$482,Lancamentos!$E$2:$E$482,"Despesa",Lancamentos!$H$2:$H$482,A32) -> 4401.71 | D32: =B32-C32 -> 1229.35 | E32: =IFERROR(D32/B32,0) -> 0.21831591 | F32: =F31+D32 -> 12474.51
A33: =Listas!A11 -> 46204 | B33: =SUMIFS(Lancamentos!$F$2:$F$482,Lancamentos!$E$2:$E$482,"Receita",Lancamentos!$H$2:$H$482,A33) -> 5632.08 | C33: =SUMIFS(Lancamentos!$F$2:$F$482,Lancamentos!$E$2:$E$482,"Despesa",Lancamentos!$H$2:$H$482,A33) -> 4821.64 | D33: =B33-C33 -> 810.44 | E33: =IFERROR(D33/B33,0) -> 0.1438971 | F33: =F32+D33 -> 13284.95
A34: =Listas!A12 -> 46235 | B34: =SUMIFS(Lancamentos!$F$2:$F$482,Lancamentos!$E$2:$E$482,"Receita",Lancamentos!$H$2:$H$482,A34) -> 6221.37 | C34: =SUMIFS(Lancamentos!$F$2:$F$482,Lancamentos!$E$2:$E$482,"Despesa",Lancamentos!$H$2:$H$482,A34) -> 5138.63 | D34: =B34-C34 -> 1082.74 | E34: =IFERROR(D34/B34,0) -> 0.17403562 | F34: =F33+D34 -> 14367.69
A35: =Listas!A13 -> 46266 | B35: =SUMIFS(Lancamentos!$F$2:$F$482,Lancamentos!$E$2:$E$482,"Receita",Lancamentos!$H$2:$H$482,A35) -> 5628.35 | C35: =SUMIFS(Lancamentos!$F$2:$F$482,Lancamentos!$E$2:$E$482,"Despesa",Lancamentos!$H$2:$H$482,A35) -> 4769.98 | D35: =B35-C35 -> 858.37 | E35: =IFERROR(D35/B35,0) -> 0.15250828 | F35: =F34+D35 -> 15226.06
A36: Total | B36: =SUM(B24:B35) -> 70337.55 | C36: =SUM(C24:C35) -> 55111.49 | D36: =SUM(D24:D35) -> 15226.06 | E36: =IFERROR(D36/B36,0) -> 0.21647129 | F36: =F35 -> 15226.06

Sheet Lancamentos
A1: lancamento_id | B1: data | C1: descricao | D1: categoria | E1: tipo | F1: valor | G1: forma_pagamento | H1: mes_ref
A2: 1 | B2: 45932 | C2: Recarga transporte público | D2: Transporte | E2: Despesa | F2: 150 | G2: Pix | H2: =DATE(YEAR(B2),MONTH(B2),1) -> 45931
A3: 2 | B3: 45932 | C3: Corrida de aplicativo | D3: Transporte | E3: Despesa | F3: 29.19 | G3: Cartão de crédito | H3: =DATE(YEAR(B3),MONTH(B3),1) -> 45931
A4: 3 | B4: 45933 | C4: Academia | D4: Saúde | E4: Despesa | F4: 109.9 | G4: Cartão de crédito | H4: =DATE(YEAR(B4),MONTH(B4),1) -> 45931
A5: 4 | B5: 45933 | C5: Supermercado | D5: Alimentação | E5: Despesa | F5: 104.98 | G5: Pix | H5: =DATE(YEAR(B5),MONTH(B5),1) -> 45931
A6: 5 | B6: 45933 | C6: Corrida de aplicativo | D6: Transporte | E6: Despesa | F6: 34.24 | G6: Cartão de crédito | H6: =DATE(YEAR(B6),MONTH(B6),1) -> 45931
A7: 6 | B7: 45934 | C7: Consulta médica | D7: Saúde | E7: Despesa | F7: 237.97 | G7: Pix | H7: =DATE(YEAR(B7),MONTH(B7),1) -> 45931
A8: 7 | B8: 45934 | C8: Restaurante | D8: Alimentação | E8: Despesa | F8: 38.77 | G8: Cartão de crédito | H8: =DATE(YEAR(B8),MONTH(B8),1) -> 45931
A9: 8 | B9: 45934 | C9: Delivery | D9: Alimentação | E9: Despesa | F9: 66.87 | G9: Cartão de crédito | H9: =DATE(YEAR(B9),MONTH(B9),1) -> 45931
A10: 9 | B10: 45935 | C10: Salário | D10: Salário | E10: Receita | F10: 5600 | G10: Pix | H10: =DATE(YEAR(B10),MONTH(B10),1) -> 45931
A11: 10 | B11: 45935 | C11: Restaurante | D11: Alimentação | E11: Despesa | F11: 47.72 | G11: Pix | H11: =DATE(YEAR(B11),MONTH(B11),1) -> 45931
A12: 11 | B12: 45936 | C12: Curso online | D12: Educação | E12: Despesa | F12: 59.9 | G12: Cartão de crédito | H12: =DATE(YEAR(B12),MONTH(B12),1) -> 45931
A13: 12 | B13: 45936 | C13: Show | D13: Lazer | E13: Despesa | F13: 86.19 | G13: Débito | H13: =DATE(YEAR(B13),MONTH(B13),1) -> 45931
... A482: 481 | B482: 46293 | C482: Corrida de aplicativo | D482: Transporte | E482: Despesa | F482: 26.07 | G482: Cartão de crédito | H482: =DATE(YEAR(B482),MONTH(B482),1) -> 46266

Sheet Orcamento
A1: categoria | B1: orcamento_mensal | D1: Valores em azul são premissas: altere e o Resumo recalcula.
A2: Moradia | B2: 1900
A3: Alimentação | B3: 1100
A4: Transporte | B4: 450
A5: Saúde | B5: 250
A6: Lazer | B6: 400
A7: Educação | B7: 200
A8: Assinaturas | B8: 120
A9: Compras | B9: 350
A10: Outros | B10: 200
A11: Total | B11: =SUM(B2:B10) -> 4970

Sheet Listas
A1: mes
A2: =DATE(2025,10,1) -> 45931
A3: =EDATE(A2,1) -> 45962
A4: =EDATE(A3,1) -> 45992
A5: =EDATE(A4,1) -> 46023
A6: =EDATE(A5,1) -> 46054
A7: =EDATE(A6,1) -> 46082
A8: =EDATE(A7,1) -> 46113
A9: =EDATE(A8,1) -> 46143
A10: =EDATE(A9,1) -> 46174
A11: =EDATE(A10,1) -> 46204
A12: =EDATE(A11,1) -> 46235
A13: =EDATE(A12,1) -> 46266

Sheet Premissas
A1: Sobre este projeto
A2: Controle financeiro de uma pessoa fictícia, de out/2025 a set/2026. Os dados são simulados por script Python (gerar_dados.py, semente fixa) e não representam finanças reais.
A4: Como usar
A5: Resumo: escolha o mês na célula amarela (B4) e veja indicadores e orçado x realizado. Lancamentos: base de dados (tabela tbl_lancamentos). Orcamento: metas mensais por categoria, editáveis (valores em azul).
A6: A coluna mes_ref da aba Lancamentos é fórmula auxiliar (primeiro dia do mês de cada data).
A8: Regras de leitura
A9: Status do orçamento: OK até 90% do orçado, Atenção de 90% a 100%, Estourou acima de 100%.
A10: Taxa de poupança = (receitas − despesas) ÷ receitas.
